{
    "1": "Top Drive Track",
    "2": "Pilot Unit",
    "3": "Power Module",
    "4": "Top Drive Track",
    "5": "Pilot Unit",
    "6": "Power Module",
    "7": "Top Drive Track",
    "8": "Pilot Unit",
    "9": "Power Module",
    "10": "Top Drive Track",
    "11": "Pilot Unit",
    "12": "Power Module",
    "13": "Top Drive Track",
    "14": "Pilot Unit",
    "15": "Power Module",
    "16": "Top Drive Track",
    "17": "Pilot Unit",
    "18": "Power Module",
    "19": "Top Drive Track",
    "20": "Pilot Unit",
    "21": "Power Module",
    "22": "Top Drive Track",
    "23": "Pilot Unit",
    "24": "Power Module"
}