[
    {
        "Id": 1,
        "AxisName": "Zoom",
        "AxisType": 1,
        "PcKeyMap": [],
        "GamepadKeyMap": [
            {
                "key": "Gamepad_LeftTriggerAxis",
                "value": "Gamepad_LeftShoulder"
            },
            {
                "key": "Gamepad_RightTriggerAxis",
                "value": "Gamepad_LeftShoulder"
            }
        ],
        "SecondaryKeyScaleMap": [
            {
                "key": "Up",
                "value": 1.0
            },
            {
                "key": "Down",
                "value": -1.0
            },
            {
                "key": "Gamepad_LeftTriggerAxis",
                "value": -80.0
            },
            {
                "key": "Gamepad_RightTriggerAxis",
                "value": 80.0
            }
        ],
        "MobileIconPath": "",
        "DisplayName": "",
        "KeyboardVersion": 0,
        "GamepadVersion": 0
    }
]